nonebot_plugin_WWwiki/__init__.py
nonebot_plugin_WWwiki/activities.py
nonebot_plugin_WWwiki/basicinformation.py
nonebot_plugin_WWwiki/config.py
nonebot_plugin_WWwiki/data/activities.json
nonebot_plugin_WWwiki/echo.py
nonebot_plugin_WWwiki/echocard.py
nonebot_plugin_WWwiki/enemy.py
nonebot_plugin_WWwiki/getarchives.py
nonebot_plugin_WWwiki/getmaterial.py
nonebot_plugin_WWwiki/getskll.py
nonebot_plugin_WWwiki/html_template/activity/template.html
nonebot_plugin_WWwiki/html_template/archives/template.html
nonebot_plugin_WWwiki/html_template/classify/template.html
nonebot_plugin_WWwiki/html_template/echo/template.html
nonebot_plugin_WWwiki/html_template/echolink/template.html
nonebot_plugin_WWwiki/html_template/enemy/template.html
nonebot_plugin_WWwiki/html_template/fonts/FZShuTi.ttf
nonebot_plugin_WWwiki/html_template/fonts/STXingkai.ttf
nonebot_plugin_WWwiki/html_template/fonts/SanJiHuaChaoTi-Zhong-2.ttf
nonebot_plugin_WWwiki/html_template/gift/template.html
nonebot_plugin_WWwiki/html_template/img/Zinc.jpg
nonebot_plugin_WWwiki/html_template/img/logo.png
nonebot_plugin_WWwiki/html_template/materialcard/img/e93296bb45e74a0e9e523120e317794620240521.png
nonebot_plugin_WWwiki/html_template/materialcard/img/分割1.png
nonebot_plugin_WWwiki/html_template/materialcard/img/头.png
nonebot_plugin_WWwiki/html_template/materialcard/img/画板 4-7.png
nonebot_plugin_WWwiki/html_template/materialcard/img/葫芦.png
nonebot_plugin_WWwiki/html_template/materialcard/img/贝币.png
nonebot_plugin_WWwiki/html_template/materialcard/template.html
nonebot_plugin_WWwiki/html_template/recommendation/template.html
nonebot_plugin_WWwiki/html_template/rolecard/template.html
nonebot_plugin_WWwiki/html_template/skllcard/template.html
nonebot_plugin_WWwiki/html_template/tale/template.html
nonebot_plugin_WWwiki/html_template/timing/template.html
nonebot_plugin_WWwiki/html_template/weapon/template.html
nonebot_plugin_WWwiki/html_template/yituliu/template.html
nonebot_plugin_WWwiki/itemlink.py
nonebot_plugin_wwwiki-0.4.1.dist-info/METADATA
nonebot_plugin_wwwiki-0.4.1.dist-info/WHEEL
nonebot_plugin_wwwiki-0.4.1.dist-info/entry_points.txt
nonebot_plugin_wwwiki-0.4.1.dist-info/licenses/LICENSE
nonebot_plugin_wwwiki-0.4.1.dist-info/RECORD
