Metadata-Version: 2.1
Name: nonebot-plugin-WWwiki
Version: 0.4.1
Summary: 发送kurobbs的数据
Author-Email: rf_tar_railt <3165388245@qq.com>, shiyingyingjiang <2798134864@qq.com>
License: MIT
Project-URL: homepage, https://github.com/shi-yingyingjiang/nonebot-plugin-WWwiki
Project-URL: repository, https://github.com/shi-yingyingjiang/nonebot-plugin-WWwiki
Requires-Python: >=3.9
Requires-Dist: jinja2>=3.1.2
Requires-Dist: pandas>=2.0.3
Requires-Dist: pydantic>=1.10.11
Requires-Dist: Pillow>=9.4.0
Requires-Dist: beautifulsoup4>=4.12.3
Requires-Dist: nonebot2[httpx]>=2.3.0
Requires-Dist: nonebot-plugin-alconna>=0.52.2
Requires-Dist: nonebot-plugin-uninfo>=0.6.5
Requires-Dist: nonebot-plugin-htmlrender>=0.3.2
Requires-Dist: nonebot-plugin-apscheduler>=0.5.0
Requires-Dist: lxml>=5.2.2
Requires-Dist: matplotlib>=3.10.0
Requires-Dist: pypinyin>=0.53.0
